[
    {
        "word": "by",
        "nearest_words": [
            [
                "By",
                0.7749263644218445
            ],
            [
                "\u017c\u0119by",
                0.6117103695869446
            ],
            [
                "muc",
                0.5993669033050537
            ],
            [
                "D\u00e1bh\u00ed",
                0.5797327756881714
            ],
            [
                "\u017cey",
                0.5621424317359924
            ]
        ],
        "label": "Wzmacnianie"
    },
    {
        "word": "kto",
        "nearest_words": [
            [
                "Kto",
                0.7983403205871582
            ],
            [
                "kto\u015b",
                0.7827781438827515
            ],
            [
                "Kto\u015b",
                0.7355507612228394
            ],
            [
                "ktokolwiek",
                0.7244020104408264
            ],
            [
                "nikt",
                0.7062694430351257
            ]
        ],
        "label": "Wzmacnianie"
    },
    {
        "word": "\"",
        "nearest_words": [
            [
                "\u201e",
                0.7136688232421875
            ],
            [
                "\u201d",
                0.6896897554397583
            ],
            [
                "\u76f8\u64b2",
                0.6212580800056458
            ],
            [
                "'",
                0.6117698550224304
            ],
            [
                "pt",
                0.6049278378486633
            ]
        ],
        "label": "Wzmacnianie"
    },
    {
        "word": "odbiorcow",
        "nearest_words": [
            [
                "dostawcow",
                0.7481265664100647
            ],
            [
                "inwestorow",
                0.7376876473426819
            ],
            [
                "kontrahentow",
                0.7156268954277039
            ],
            [
                "przedsiebiorcow",
                0.7137803435325623
            ],
            [
                "sprzedawcow",
                0.7125570774078369
            ]
        ],
        "label": "Wzmacnianie"
    },
    {
        "word": "\"",
        "nearest_words": [
            [
                "\u201e",
                0.7136688232421875
            ],
            [
                "\u201d",
                0.6896897554397583
            ],
            [
                "\u76f8\u64b2",
                0.6212580800056458
            ],
            [
                "'",
                0.6117698550224304
            ],
            [
                "pt",
                0.6049278378486633
            ]
        ],
        "label": "Wzmacnianie"
    },
    {
        "word": "cz\u0142owiek",
        "nearest_words": [
            [
                "Cz\u0142owiek",
                0.8008051514625549
            ],
            [
                "czlowiek",
                0.7632810473442078
            ],
            [
                "cz\u0142owiek.",
                0.6931189298629761
            ],
            [
                "cz\u0142owiek-",
                0.6911522746086121
            ],
            [
                ".Cz\u0142owiek",
                0.6798081398010254
            ]
        ],
        "label": "Wzmacnianie"
    },
    {
        "word": "kojarzy\u0107",
        "nearest_words": [
            [
                "kojarzy",
                0.801429808139801
            ],
            [
                "skojarzy\u0107",
                0.7774142622947693
            ],
            [
                "kojarzy\u0142",
                0.7594692707061768
            ],
            [
                "kojarz\u0105",
                0.7483085989952087
            ],
            [
                "kojarzyc",
                0.743949294090271
            ]
        ],
        "label": "Wzmacnianie"
    },
    {
        "word": "seks",
        "nearest_words": [
            [
                "sex",
                0.8039870858192444
            ],
            [
                "seks.",
                0.784582257270813
            ],
            [
                "seksSeks",
                0.7590274214744568
            ],
            [
                "seks-",
                0.7556676864624023
            ],
            [
                "-seks",
                0.7375281453132629
            ]
        ],
        "label": "Wzmacnianie"
    },
    {
        "word": "dziwi\u0107",
        "nearest_words": [
            [
                "dziwi\u0107-",
                0.8407928347587585
            ],
            [
                "dziwi\u0107.",
                0.7670019865036011
            ],
            [
                "dziwi",
                0.7570365071296692
            ],
            [
                "Dziwi\u0107",
                0.7534852027893066
            ],
            [
                "dziwic",
                0.7349650263786316
            ]
        ],
        "label": "Wzmacnianie"
    },
    {
        "word": "fakt",
        "nearest_words": [
            [
                "faktem",
                0.6765090823173523
            ],
            [
                "faktu",
                0.6615055799484253
            ],
            [
                "Fakt",
                0.653268039226532
            ],
            [
                "zwa\u017cywszy",
                0.639374315738678
            ],
            [
                "Faktem",
                0.6269975900650024
            ]
        ],
        "label": "Wzmacnianie"
    },
    {
        "word": "zdrajca",
        "nearest_words": [
            [
                "Zdrajca",
                0.6209378838539124
            ],
            [
                "patriota",
                0.6066537499427795
            ],
            [
                "zdrajco",
                0.5997114181518555
            ],
            [
                "zdrajc\u0105",
                0.5995821356773376
            ],
            [
                "s\u0142ugus",
                0.576718807220459
            ]
        ],
        "label": "Wzmacnianie"
    },
    {
        "word": "faszysty",
        "nearest_words": [
            [
                "faszyst\u0119",
                0.766878068447113
            ],
            [
                "antyfaszysty",
                0.7212908864021301
            ],
            [
                "faszysta",
                0.6960245966911316
            ],
            [
                "nacjonalisty",
                0.6778904795646667
            ],
            [
                "nazisty",
                0.6616714596748352
            ]
        ],
        "label": "Wzmacnianie"
    },
    {
        "word": "Ryju",
        "nearest_words": [
            [
                "Bzim",
                0.6413260698318481
            ],
            [
                "Quka",
                0.5929113626480103
            ],
            [
                "Gufi",
                0.5825026631355286
            ],
            [
                "Czizz",
                0.5725862383842468
            ],
            [
                "Ygor",
                0.5625435709953308
            ]
        ],
        "label": "Wzmacnianie"
    },
    {
        "word": "krystyna",
        "nearest_words": [
            [
                "krystynaa",
                0.7518457174301147
            ],
            [
                "krystyny",
                0.7019952535629272
            ],
            [
                "marzena",
                0.6965299844741821
            ],
            [
                "zuzanna",
                0.6897120475769043
            ],
            [
                "krysia",
                0.689241349697113
            ]
        ],
        "label": "Wzmacnianie"
    },
    {
        "word": "krystyna",
        "nearest_words": [
            [
                "krystynaa",
                0.7518457174301147
            ],
            [
                "krystyny",
                0.7019952535629272
            ],
            [
                "marzena",
                0.6965299844741821
            ],
            [
                "zuzanna",
                0.6897120475769043
            ],
            [
                "krysia",
                0.689241349697113
            ]
        ],
        "label": "Wzmacnianie"
    },
    {
        "word": "but",
        "nearest_words": [
            [
                "But",
                0.6688135266304016
            ],
            [
                "INVOKE",
                0.5917161107063293
            ],
            [
                "No-One",
                0.5186284780502319
            ],
            [
                "bucik",
                0.49525022506713867
            ],
            [
                "tired",
                0.4875282347202301
            ]
        ],
        "label": "Wzmacnianie"
    },
    {
        "word": "dziwi\u0107",
        "nearest_words": [
            [
                "dziwi\u0107-",
                0.8407928347587585
            ],
            [
                "dziwi\u0107.",
                0.7670019865036011
            ],
            [
                "dziwi",
                0.7570365071296692
            ],
            [
                "Dziwi\u0107",
                0.7534852027893066
            ],
            [
                "dziwic",
                0.7349650263786316
            ]
        ],
        "label": "Wzmacnianie"
    },
    {
        "word": "zdrajca",
        "nearest_words": [
            [
                "Zdrajca",
                0.6209378838539124
            ],
            [
                "patriota",
                0.6066537499427795
            ],
            [
                "zdrajco",
                0.5997114181518555
            ],
            [
                "zdrajc\u0105",
                0.5995821356773376
            ],
            [
                "s\u0142ugus",
                0.576718807220459
            ]
        ],
        "label": "Strenghtening"
    },
    {
        "word": "faszysty",
        "nearest_words": [
            [
                "faszyst\u0119",
                0.766878068447113
            ],
            [
                "antyfaszysty",
                0.7212908864021301
            ],
            [
                "faszysta",
                0.6960245966911316
            ],
            [
                "nacjonalisty",
                0.6778904795646667
            ],
            [
                "nazisty",
                0.6616714596748352
            ]
        ],
        "label": "Strenghtening"
    }
]